<?xml version="1.0" encoding="utf-8"?>
<records>
	<record>
		<region>阿根廷</region>
		<name>阿根廷披索</name>
		<iso4217>ARS</iso4217>
	</record>
	<record>
		<region>澳洲</region>
		<name>澳幣</name>
		<iso4217>AUD</iso4217>
	</record>
	<record>
		<region>巴林</region>
		<name>巴林第納爾</name>
		<iso4217>BHD</iso4217>
	</record>
	<record>
		<region>巴貝多</region>
		<name>巴貝多元</name>
		<iso4217>BBD</iso4217>
	</record>
	<record>
		<region>玻利維亞</region>
		<name>玻利維亞貨幣單位</name>
		<iso4217>BOB</iso4217>
	</record>
	<record>
		<region>巴西</region>
		<name>巴西里拉</name>
		<iso4217>BRL</iso4217>
	</record>
	<record>
		<region>英國</region>
		<name>英鎊</name>
		<iso4217>GBP</iso4217>
	</record>
	<record>
		<region>加拿大</region>
		<name>加幣</name>
		<iso4217>CAD</iso4217>
	</record>
	<record>
		<region>喀麥隆</region>
		<name>法郎 (CFA-BEAC)</name>
		<iso4217>XAF</iso4217>
	</record>
	<record>
		<region>智利</region>
		<name>智利披索</name>
		<iso4217>CLP</iso4217>
	</record>
	<record>
		<region>中華人民共和國</region>
		<name>人民幣</name>
		<iso4217>CNY</iso4217>
	</record>
	<record>
		<region>哥倫比亞</region>
		<name>哥倫比亞披索</name>
		<iso4217>COP</iso4217>
	</record>
	<record>
		<region>捷克共和國</region>
		<name>捷克克朗</name>
		<iso4217>CZK</iso4217>
	</record>
	<record>
		<region>丹麥</region>
		<name>丹麥克羅納</name>
		<iso4217>DKK</iso4217>
	</record>
	<record>
		<region>安地卡及巴布達</region>
		<name>格瑞那達元</name>
		<iso4217>XCD</iso4217>
	</record>
	<record>
		<region>埃及</region>
		<name>埃及鎊</name>
		<iso4217>EGP</iso4217>
	</record>
	<record>
		<region>阿拉伯聯合大公國</region>
		<name>阿拉伯聯合大公國迪爾汗</name>
		<iso4217>AED</iso4217>
	</record>
	<record>
		<region>歐元區</region>
		<name>歐元</name>
		<iso4217>EUR</iso4217>
	</record>
	<record>
		<region>香港</region>
		<name>港幣</name>
		<iso4217>HKD</iso4217>
	</record>
	<record>
		<region>匈牙利</region>
		<name>匈牙利福林</name>
		<iso4217>HUF</iso4217>
	</record>
	<record>
		<region>冰島</region>
		<name>冰島克朗</name>
		<iso4217>ISK</iso4217>
	</record>
	<record>
		<region>印度</region>
		<name>印度盧比</name>
		<iso4217>INR</iso4217>
	</record>
	<record>
		<region>印尼</region>
		<name>印尼盾</name>
		<iso4217>IDR</iso4217>
	</record>
	<record>
		<region>以色列</region>
		<name>以色列新謝克爾</name>
		<iso4217>ILS</iso4217>
	</record>
	<record>
		<region>牙買加</region>
		<name>牙買加元</name>
		<iso4217>JMD</iso4217>
	</record>
	<record>
		<region>日本</region>
		<name>日圓</name>
		<iso4217>JPY</iso4217>
	</record>
	<record>
		<region>約旦</region>
		<name>約旦第納爾</name>
		<iso4217>JOD</iso4217>
	</record>
	<record>
		<region>肯亞</region>
		<name>肯尼亞先令</name>
		<iso4217>KES</iso4217>
	</record>
	<record>
		<region>南韓</region>
		<name>韓圜</name>
		<iso4217>KRW</iso4217>
	</record>
	<record>
		<region>科威特</region>
		<name>科威特第納爾</name>
		<iso4217>KWD</iso4217>
	</record>
	<record>
		<region>拉脫維亞</region>
		<name>立陶宛里塔</name>
		<iso4217>LVL</iso4217>
	</record>
	<record>
		<region>黎巴嫩</region>
		<name>黎巴嫩鎊</name>
		<iso4217>LBP</iso4217>
	</record>
	<record>
		<region>立陶宛</region>
		<name>立陶宛里塔</name>
		<iso4217>LTL</iso4217>
	</record>
	<record>
		<region>馬來西亞</region>
		<name>馬來西亞令吉</name>
		<iso4217>MYR</iso4217>
	</record>
	<record>
		<region>墨西哥</region>
		<name>墨西哥披索</name>
		<iso4217>MXN</iso4217>
	</record>
	<record>
		<region>摩洛哥</region>
		<name>摩洛哥迪拉姆</name>
		<iso4217>MAD</iso4217>
	</record>
	<record>
		<region>納米比亞</region>
		<name>納米比亞元</name>
		<iso4217>NAD</iso4217>
	</record>
	<record>
		<region>尼日</region>
		<name>尼泊爾盧布</name>
		<iso4217>NPR</iso4217>
	</record>
	<record>
		<region>土耳其</region>
		<name>新土耳其里拉</name>
		<iso4217>TRY</iso4217>
	</record>
	<record>
		<region>紐西蘭</region>
		<name>紐西蘭幣</name>
		<iso4217>NZD</iso4217>
	</record>
	<record>
		<region>尼日</region>
		<name>法郎 (CFA-BCEAO)</name>
		<iso4217>XOF</iso4217>
	</record>
	<record>
		<region>奈及利亞</region>
		<name>奈及利亞奈拉</name>
		<iso4217>NGN</iso4217>
	</record>
	<record>
		<region>挪威</region>
		<name>挪威克羅納</name>
		<iso4217>NOK</iso4217>
	</record>
	<record>
		<region>阿曼王國</region>
		<name>阿曼里奧</name>
		<iso4217>OMR</iso4217>
	</record>
	<record>
		<region>巴基斯坦</region>
		<name>巴基斯坦盧布</name>
		<iso4217>PKR</iso4217>
	</record>
	<record>
		<region>巴拿馬</region>
		<name>巴拿馬巴波亞</name>
		<iso4217>PAB</iso4217>
	</record>
	<record>
		<region>秘魯</region>
		<name>秘魯新太陽幣</name>
		<iso4217>PEN</iso4217>
	</record>
	<record>
		<region>菲律賓</region>
		<name>菲律賓披索</name>
		<iso4217>PHP</iso4217>
	</record>
	<record>
		<region>波蘭</region>
		<name>波蘭茲羅提</name>
		<iso4217>PLN</iso4217>
	</record>
	<record>
		<region>卡達</region>
		<name>卡達爾里亞爾</name>
		<iso4217>QAR</iso4217>
	</record>
	<record>
		<region>羅馬尼亞</region>
		<name>羅馬尼亞列伊</name>
		<iso4217>RON</iso4217>
	</record>
	<record>
		<region>俄羅斯</region>
		<name>俄羅斯盧布</name>
		<iso4217>RUB</iso4217>
	</record>
	<record>
		<region>沙烏地阿拉伯</region>
		<name>沙烏地里雅</name>
		<iso4217>SAR</iso4217>
	</record>
	<record>
		<region>新加坡</region>
		<name>新加坡幣</name>
		<iso4217>SGD</iso4217>
	</record>
	<record>
		<region>南非</region>
		<name>南非蘭特</name>
		<iso4217>ZAR</iso4217>
	</record>
	<record>
		<region>斯里蘭卡</region>
		<name>斯里蘭卡盧布</name>
		<iso4217>LKR</iso4217>
	</record>
	<record>
		<region>瑞典</region>
		<name>瑞典克羅納</name>
		<iso4217>SEK</iso4217>
	</record>
	<record>
		<region>瑞士</region>
		<name>瑞士法郎</name>
		<iso4217>CHF</iso4217>
	</record>
	<record>
		<region>台灣</region>
		<name>新臺幣</name>
		<symbol>$</symbol>
		<iso4217>TWD</iso4217>
	</record>
	<record>
		<region>泰國</region>
		<name>泰銖</name>
		<iso4217>THB</iso4217>
	</record>
	<record>
		<region>烏克蘭</region>
		<name>烏克蘭格里夫那</name>
		<iso4217>UAH</iso4217>
	</record>
	<record>
		<region>烏拉圭</region>
		<name>烏拉圭披索</name>
		<iso4217>UYU</iso4217>
	</record>
	<record>
		<region>美國</region>
		<name>美金</name>
		<iso4217>USD</iso4217>
	</record>
	<record>
		<region>委內瑞拉</region>
		<name>委內瑞拉強勢玻利瓦</name>
		<iso4217>VEF</iso4217>
	</record>
	<record>
		<region>越南</region>
		<name>越南盾</name>
		<iso4217>VND</iso4217>
	</record>
	<record>
		<region>阿路巴</region>
		<name>阿魯巴盾</name>
		<iso4217>AWG</iso4217>
	</record>
	<record>
		<region>波士尼亞與赫塞格維納</region>
		<name>波士尼亞-黑塞哥維那可轉換馬克</name>
		<iso4217>BAM</iso4217>
	</record>
	<record>
		<region>孟加拉</region>
		<name>孟加拉塔卡</name>
		<iso4217>BDT</iso4217>
	</record>
	<record>
		<region>保加利亞</region>
		<name>保加利亞新列弗</name>
		<iso4217>BGN</iso4217>
	</record>
	<record>
		<region>百慕達</region>
		<name>百慕達幣</name>
		<iso4217>BMD</iso4217>
	</record>
	<record>
		<region>巴哈馬</region>
		<name>巴哈馬元</name>
		<iso4217>BSD</iso4217>
	</record>
	<record>
		<region>斐濟</region>
		<name>斐濟元</name>
		<iso4217>FJD</iso4217>
	</record>
	<record>
		<region>迦納</region>
		<name>迦納仙蔕</name>
		<iso4217>GHS</iso4217>
	</record>
	<record>
		<region>甘比亞</region>
		<name>甘比亞達拉西</name>
		<iso4217>GMD</iso4217>
	</record>
	<record>
		<region>瓜地馬拉</region>
		<name>瓜地馬拉格查爾</name>
		<iso4217>GTQ</iso4217>
	</record>
	<record>
		<region>克羅埃西亞</region>
		<name>克羅地亞庫納</name>
		<iso4217>HRK</iso4217>
	</record>
	<record>
		<region>柬埔寨</region>
		<name>柬埔寨瑞爾</name>
		<iso4217>KHR</iso4217>
	</record>
	<record>
		<region>寮國</region>
		<name>寮國基普</name>
		<iso4217>LAK</iso4217>
	</record>
	<record>
		<region>摩爾多瓦</region>
		<name>摩杜雲列伊</name>
		<iso4217>MDL</iso4217>
	</record>
	<record>
		<region>馬達加斯加</region>
		<name>馬達加斯加艾瑞爾</name>
		<iso4217>MGA</iso4217>
	</record>
	<record>
		<region>馬其頓</region>
		<name>馬其頓第納爾</name>
		<iso4217>MKD</iso4217>
	</record>
	<record>
		<region>模里西斯</region>
		<name>模里西斯盧布</name>
		<iso4217>MUR</iso4217>
	</record>
	<record>
		<region>馬爾地夫</region>
		<name>馬爾地夫海島盧非亞</name>
		<iso4217>MVR</iso4217>
	</record>
	<record>
		<region>巴拉圭</region>
		<name>巴拉圭瓜拉尼</name>
		<iso4217>PYG</iso4217>
	</record>
	<record>
		<region>塞爾維亞</region>
		<name>塞爾維亞戴納</name>
		<iso4217>RSD</iso4217>
	</record>
	<record>
		<region>塞席爾</region>
		<name>塞席爾盧比 </name>
		<iso4217>SCR</iso4217>
	</record>
	<record>
		<region>敘利亞</region>
		<name>敘利亞鎊</name>
		<iso4217>SYP</iso4217>
	</record>
	<record>
		<region>突尼西亞</region>
		<name>突尼西亞第納爾</name>
		<iso4217>TND</iso4217>
	</record>
	<record>
		<region>烏干達</region>
		<name>烏干達先令</name>
		<iso4217>UGX</iso4217>
	</record>
	<record>
		<region>法屬玻里尼西亞</region>
		<name>法郎 (CFP)</name>
		<iso4217>XPF</iso4217>
	</record>
</records>	